{
  "words": [
    {"word":"Gobierno","clues":["País","Poder","Estado","Ministros","Dirigir"],"category":"politics_and_law"},
    {"word":"Ley","clues":["Regla","Justicia","Papel","Obligatorio","Código"],"category":"politics_and_law"},
    {"word":"Juez","clues":["Juicio","Tribunal","Justicia","Sentencia","Mazo"],"category":"politics_and_law"},
    {"word":"Abogado","clues":["Defensa","Leyes","Juicio","Cliente","Derecho"],"category":"politics_and_law"},
    {"word":"Elecciones","clues":["Votar","Urna","Políticos","Democracia","Pueblo"],"category":"politics_and_law"},
    {"word":"Voto","clues":["Elecciones","Elegir","Papel","Derecho","Urna"],"category":"politics_and_law"},
    {"word":"Democracia","clues":["Libertad","Pueblo","Votar","Sistema","Derechos"],"category":"politics_and_law"},
    {"word":"Presidente","clues":["Líder","País","Gobierno","Jefe","Política"],"category":"politics_and_law"},
    {"word":"Constitución","clues":["Ley","Suprema","País","Derechos","Libro"],"category":"politics_and_law"},
    {"word":"Parlamento","clues":["Políticos","Leyes","Debatir","Congreso","Cámara"],"category":"politics_and_law"},
    {"word":"Ciudadano","clues":["Persona","País","Derechos","Votar","Pueblo"],"category":"politics_and_law"},
    {"word":"Justicia","clues":["Equidad","Ley","Balanza","Juez","Derecho"],"category":"politics_and_law"},
    {"word":"Juicio","clues":["Tribunal","Juez","Acusado","Veredicto","Justicia"],"category":"politics_and_law"},
    {"word":"Cárcel","clues":["Prisión","Delito","Castigo","Celdas","Reo"],"category":"politics_and_law"},
    {"word":"Policía","clues":["Seguridad","Ley","Uniforme","Proteger","Orden"],"category":"politics_and_law"},
    {"word":"Derechos Humanos","clues":["Personas","Mundo","Libertad","Igualdad","Protección"],"category":"politics_and_law"},
    {"word":"Tratado","clues":["Acuerdo","Países","Internacional","Firma","Paz"],"category":"politics_and_law"},
    {"word":"Embajada","clues":["País","Extranjero","Diplomacia","Cónsul","Edificio"],"category":"politics_and_law"},
    {"word":"Candidato","clues":["Elecciones","Político","Votar","Persona","Campaña"],"category":"politics_and_law"},
    {"word":"Ministro","clues":["Gobierno","Cartera","Político","Departamento","Estado"],"category":"politics_and_law"},
    {"word":"Sufragio","clues":["Voto","Derecho","Elecciones","Pueblo","Democracia"],"category":"politics_and_law"},
    {"word":"Dictadura","clues":["Régimen","Poder","Autoritario","Líder","Represión"],"category":"politics_and_law"},
    {"word":"Monarquía","clues":["Rey","Reina","Corona","Dinastía","País"],"category":"politics_and_law"},
    {"word":"Anarquía","clues":["Sin Gobierno","Caos","Desorden","Libertad Absoluta","Sin Ley"],"category":"politics_and_law"},
    {"word":"Socialismo","clues":["Igualdad","Propiedad Pública","Estado","Economía Planificada","Política"],"category":"politics_and_law"},
    {"word":"Capitalismo","clues":["Mercado Libre","Propiedad Privada","Competencia","Economía de Mercado","Política"],"category":"politics_and_law"},
    {"word":"Comunismo","clues":["Igualdad Total","Propiedad Común","Sin Clases Sociales","Revolución Proletaria","Política"],"category":"politics_and_law"},
    {"word":"Fascismo","clues":["Régimen Autoritario","Nacionalismo Extremo","Líder Carismático","Represión Política","Política"],"category":"politics_and_law"},
    {"word":"Soberanía","clues":["Independencia","Poder Supremo","Estado","Autonomía","Política"],"category":"politics_and_law"},
    {"word":"Diplomacia","clues":["Relaciones Internacionales","Negociación","Embajada","Tratado","Política"],"category":"politics_and_law"},
    {"word":"Corrupción","clues":["Soborno","Desvío de Fondos","Ilegalidad","Abuso de Poder","Política"],"category":"politics_and_law"},
    {"word":"Censura","clues":["Control de Información","Restricción","Libertad de Expresión","Gobierno","Política"],"category":"politics_and_law"},
    {"word":"Revolución","clues":["Cambio Radical","Pueblo","Líder","Política","Historia"],"category":"politics_and_law"},
    {"word":"Guerra","clues":["Conflicto","Armas","Ejército","Países","Política"],"category":"politics_and_law"},
    {"word":"Paz","clues":["Armisticio","Acuerdo","Diplomacia","Tratado","Política"],"category":"politics_and_law"},
    {"word":"Inmigración","clues":["Migración","País","Emigración","Refugiados","Política"],"category":"politics_and_law"},
    {"word":"Emigración","clues":["Migración","País","Inmigración","Refugiados","Política"],"category":"politics_and_law"},
    {"word":"Refugiados","clues":["Guerra","Persecución","Inmigración","Emigración","Política"],"category":"politics_and_law"},
    {"word":"Sanciones","clues":["Castigo","Países","Economía","Política","Internacional"],"category":"politics_and_law"},
    {"word":"Bloqueo","clues":["Restricción","Países","Comercio","Política","Económico"],"category":"politics_and_law"},
    {"word":"Embargo","clues":["Prohibición","Comercio","Países","Política","Económico"],"category":"politics_and_law"},
    {"word":"Crisis Política","clues":["Inestabilidad","Gobierno","Protestas","Economía","Política"],"category":"politics_and_law"},
    {"word":"Corrupción Política","clues":["Soborno","Desvío de Fondos","Ilegalidad","Abuso de Poder","Política"],"category":"politics_and_law"},
    {"word":"Populismo","clues":["Líder Carismático","Promesas Irrealizables","Demagogia","Política","Pueblo"],"category":"politics_and_law"},
    {"word":"Globalización Política","clues":["Interconexión Mundial","Relaciones Internacionales","Organizaciones Globales","Política","Economía"],"category":"politics_and_law"}
  ]
}