{
  "words": [
    {"word":"Escuela","clues":["Aprender","Niños","Edificio","Clases","Maestro"],"category":"school_and_education"},
    {"word":"Universidad","clues":["Grado","Carrera","Estudiar","Campus","Título"],"category":"school_and_education"},
    {"word":"Examen","clues":["Prueba","Nota","Estudiar","Papel","Aprobar"],"category":"school_and_education"},
    {"word":"Mochila","clues":["Libros","Espalda","Cargar","Escuela","Material"],"category":"school_and_education"},
    {"word":"Cuaderno","clues":["Escribir","Papel","Apuntes","Hojas","Lápiz"],"category":"school_and_education"},
    {"word":"Lápiz","clues":["Escribir","Grafito","Madera","Goma","Dibujar"],"category":"school_and_education"},
    {"word":"Bolígrafo","clues":["Tinta","Escribir","Azul","Papel","Oficina"],"category":"school_and_education"},
    {"word":"Pizarra","clues":["Tiza","Clase","Pared","Escribir","Verde"],"category":"school_and_education"},
    {"word":"Pupitre","clues":["Mesa","Silla","Clase","Sentarse","Alumno"],"category":"school_and_education"},
    {"word":"Biblioteca","clues":["Libros","Silencio","Estudiar","Estantería","Préstamo"],"category":"school_and_education"},
    {"word":"Recreo","clues":["Jugar","Descanso","Patio","Escuela","Merienda"],"category":"school_and_education"},
    {"word":"Diccionario","clues":["Palabras","Significado","Libro","Definición","Letras"],"category":"school_and_education"},
    {"word":"Matemáticas","clues":["Números","Cálculo","Sumar","Álgebra","Geometría"],"category":"school_and_education"},
    {"word":"Historia","clues":["Pasado","Fechas","Reyes","Guerra","Antiguo"],"category":"school_and_education"},
    {"word":"Geografía","clues":["Mapas","Países","Ríos","Mundo","Tierra"],"category":"school_and_education"},
    {"word":"Ciencia","clues":["Experimento","Laboratorio","Biología","Investigar","Prueba"],"category":"school_and_education"},
    {"word":"Educación Física","clues":["Deporte","Gimnasio","Correr","Ejercicio","Chándal"],"category":"school_and_education"},
    {"word":"Tarea","clues":["Casa","Deberes","Estudiar","Después","Colegio"],"category":"school_and_education"},
    {"word":"Diploma","clues":["Título","Graduación","Papel","Éxito","Estudios"],"category":"school_and_education"},
    {"word":"Beca","clues":["Dinero","Ayuda","Estudiar","Gratis","Mérito"],"category":"school_and_education"},
    {"word":"Calculadora","clues":["Números","Cálculo","Botones","Matemáticas","Sumar"],"category":"school_and_education"},
    {"word":"Compás","clues":["Círculo","Dibujo","Geometría","Mina","Ángulo"],"category":"school_and_education"},
    {"word":"Regla","clues":["Medir","Línea","Recta","Centímetros","Plástico"],"category":"school_and_education"},
    {"word":"Goma de Borrar","clues":["Error","Lápiz","Limpiar","Papel","Frotar"],"category":"school_and_education"},
    {"word":"Sacapuntas","clues":["Lápiz","Punta","Madera","Afilado","Cuchilla"],"category":"school_and_education"},
    {"word":"Profesor","clues":["Enseñar","Clase","Maestro","Explicar","Educación"],"category":"school_and_education"},
    {"word":"Alumno","clues":["Estudiante","Aprender","Clase","Escuela","Niño"],"category":"school_and_education"},
    {"word":"Director","clues":["Jefe","Escuela","Oficina","Mando","Colegio"],"category":"school_and_education"},
    {"word":"Aula","clues":["Clase","Habitación","Pupitres","Escuela","Lección"],"category":"school_and_education"},
    {"word":"Lección","clues":["Tema","Aprender","Clase","Explicación","Libro"],"category":"school_and_education"},
    {"word":"Alfabeto","clues":["Letras","Leer","A B C","Escribir","Idioma"],"category":"school_and_education"},
    {"word":"Gramática","clues":["Idioma","Reglas","Escribir","Verbos","Lengua"],"category":"school_and_education"},
    {"word":"Literatura","clues":["Libros","Leer","Novela","Poesía","Autores"],"category":"school_and_education"},
    {"word":"Idioma","clues":["Lengua","Hablar","Inglés","Español","Traducción"],"category":"school_and_education"},
    {"word":"Laboratorio","clues":["Ciencia","Experimento","Bata","Química","Tubos"],"category":"school_and_education"},
    {"word":"Graduación","clues":["Fiesta","Final","Título","Birrete","Celebrar"],"category":"school_and_education"},
    {"word":"Semestre","clues":["Tiempo","Meses","Curso","Periodo","Mitad"],"category":"school_and_education"},
    {"word":"Horario","clues":["Tiempo","Clases","Días","Agenda","Rutina"],"category":"school_and_education"},
    {"word":"Expediente","clues":["Notas","Historial","Papel","Alumno","Registro"],"category":"school_and_education"},
    {"word":"Conferencia","clues":["Hablar","Charla","Experto","Escuchar","Universidad"],"category":"school_and_education"},
    {"word":"Mapa","clues":["Países","Dibujo","Geografía","Mundo","Papel"],"category":"school_and_education"},
    {"word":"Gimnasio","clues":["Deporte","Ejercicio","Cancha","Entrenar","Físico"],"category":"school_and_education"},
    {"word":"Comedor","clues":["Comida","Almuerzo","Escuela","Mesa","Hambre"],"category":"school_and_education"},
    {"word":"Guardería","clues":["Bebés","Niños","Cuidar","Jugar","Pequeños"],"category":"school_and_education"},
    {"word":"Bachillerato","clues":["Instituto","Estudios","Final","Universidad","Jóvenes"],"category":"school_and_education"},
    {"word":"Tesis","clues":["Grado","Investigación","Libro","Final","Doctorado"],"category":"school_and_education"},
    {"word":"Resumen","clues":["Corto","Texto","Idea","Estudiar","Puntos"],"category":"school_and_education"},
    {"word":"Enciclopedia","clues":["Información","Libros","Saber","Consulta","Datos"],"category":"school_and_education"},
    {"word":"Pluma","clues":["Tinta","Escribir","Antiguo","Estilográfica","Papel"],"category":"school_and_education"},
    {"word":"Pegamento","clues":["Pegar","Papel","Manualidades","Barra","Unir"],"category":"school_and_education"},
    {"word":"Papel","clues":["Escribir","Dibujar","Libro","Cuaderno","Oficina"],"category":"school_and_education"},
    {"word":"Tinta","clues":["Escribir","Bolígrafo","Pluma","Papel","Color"],"category":"school_and_education"},
    {"word":"Pizarra Blanca","clues":["Marcadores","Clase","Escribir","Borrar","Blanco"],"category":"school_and_education"},
    {"word":"Marcador","clues":["Pizarra Blanca","Colores","Escribir","Borrar","Clase"],"category":"school_and_education"},
    {"word":"Rotulador","clues":["Marcador","Colores","Escribir","Pizarra Blanca","Clase"],"category":"school_and_education"},
    {"word":"Carpeta","clues":["Papel","Organizar","Oficina","Escuela","Documentos"],"category":"school_and_education"},
    {"word":"Agenda","clues":["Tiempo","Días","Planificar","Horario","Calendario"],"category":"school_and_education"},
    {"word":"Calculadora Científica","clues":["Números","Funciones Avanzadas","Matemáticas Complejas"],"category":"school_and_education"},
    {"word":"Pizarra Digital","clues":["Tecnología","Interactividad","Clase Moderna"],"category":"school_and_education"},
    {"word":"Tablet Educativa","clues":["Tecnología","Portátil","Aprendizaje Digital"],"category":"school_and_education"},
    {"word":"Proyector","clues":["Presentación","Pantalla","Clase Visual"],"category":"school_and_education"},
    {"word":"Microscopio","clues":["Ciencia","Pequeño","Laboratorio"],"category":"school_and_education"},
    {"word":"Telescopio","clues":["Astronomía","Lejos","Cielo Estrellado"],"category":"school_and_education"},
    {"word":"Impresora 3D","clues":["Tecnología","Crear Objetos Físicos"],"category":"school_and_education"},
    {"word":"Patio","clues":["Recreo","Jugar","Escuela","Descanso","Niños"],"category":"school_and_education"},
    {"word":"Uniforme Escolar","clues":["Ropa","Colegio","Identidad","Estudiantes"],"category":"school_and_education"},
    {"word":"Tutoría","clues":["Apoyo","Estudiante","Profesor","Ayuda"],"category":"school_and_education"},
    {"word":"Manualidades","clues":["Arte","Hacer","Papel","Tijeras","Creatividad"],"category":"school_and_education"},
    {"word":"Proyecto Escolar","clues":["Trabajo en Grupo","Investigar","Presentar"],"category":"school_and_education"},
    {"word":"Exposición Oral","clues":["Hablar en Público","Presentar Tema"],"category":"school_and_education"},
    {"word":"Trabajo en Equipo","clues":["Colaborar","Grupo","Compartir Ideas"],"category":"school_and_education"}
  ]
}