{
  "words": [
    {"word":"Instagram","clues":["Fotos","Filtros","Historias","Influencer","Post"],"category":"social_media_and_streamers"},
    {"word":"TikTok","clues":["Vídeos","Cortos","Música","Viral","Baile"],"category":"social_media_and_streamers"},
    {"word":"Twitter","clues":["Mensajes","Pájaro","Hilos","Noticias","Tendencia"],"category":"social_media_and_streamers"},
    {"word":"YouTube","clues":["Vídeos","Canal","Botón","Suscriptores","Directo"],"category":"social_media_and_streamers"},
    {"word":"Twitch","clues":["Directo","Streamer","Chat","Morado","Gaming"],"category":"social_media_and_streamers"},
    {"word":"WhatsApp","clues":["Chat","Mensaje","Estados","Llamada","Verde"],"category":"social_media_and_streamers"},
    {"word":"Facebook","clues":["Red","Amigos","Muro","Azul","Grupos"],"category":"social_media_and_streamers"},
    {"word":"Reddit","clues":["Foro","Comunidad","Votos","Hilos","Karma"],"category":"social_media_and_streamers"},
    {"word":"Discord","clues":["Servidor","Voz","Gaming","Canales","Chat"],"category":"social_media_and_streamers"},
    {"word":"LinkedIn","clues":["Trabajo","Perfil","Empresa","Contactos","Profesional"],"category":"social_media_and_streamers"},
    {"word":"Ibai Llanos","clues":["Streamer","España","Eventos","Twitch","Velada"],"category":"social_media_and_streamers"},
    {"word":"AuronPlay","clues":["Streamer","Bromas","Twitch","España","YouTube"],"category":"social_media_and_streamers"},
    {"word":"ElRubius","clues":["YouTube","Streamer","España","Gaming","Icono"],"category":"social_media_and_streamers"},
    {"word":"MrBeast","clues":["Dinero","YouTube","Retos","Filantropía","Viral"],"category":"social_media_and_streamers"},
    {"word":"TheGrefg","clues":["Streamer","Récord","Fortnite","Contador","España"],"category":"social_media_and_streamers"},
    {"word":"Hashtag","clues":["Almohadilla","Etiqueta","Búsqueda","Tema","Tendencia"],"category":"social_media_and_streamers"},
    {"word":"Influencer","clues":["Famoso","Redes","Marcas","Seguidores","Contenido"],"category":"social_media_and_streamers"},
    {"word":"Follower","clues":["Seguidor","Número","Perfil","Redes","Fan"],"category":"social_media_and_streamers"},
    {"word":"Like","clues":["Corazón","Me gusta","Botón","Interacción","Dedo"],"category":"social_media_and_streamers"},
    {"word":"Selfie","clues":["Foto","Autorretrato","Cámara","Cara","Brazo"],"category":"social_media_and_streamers"},
    {"word":"Meme","clues":["Gracia","Imagen","Viral","Internet","Texto"],"category":"social_media_and_streamers"},
    {"word":"Hater","clues":["Odio","Comentario","Crítica","Tóxico","Redes"],"category":"social_media_and_streamers"},
    {"word":"Streamer","clues":["Cámara","Directo","En vivo","Internet","Audiencia"],"category":"social_media_and_streamers"},
    {"word":"Clickbait","clues":["Engaño","Título","Miniatura","Clic","YouTube"],"category":"social_media_and_streamers"},
    {"word":"Podcast","clues":["Audio","Micrófono","Episodio","Escuchar","Spotify"],"category":"social_media_and_streamers"},
    {"word":"Spotify","clues":["Música","Canción","Lista","Streaming","Podcast"],"category":"social_media_and_streamers"},
    {"word":"Snapchat","clues":["Fantasma","Filtros","Efímero","Racha","Fotos"],"category":"social_media_and_streamers"},
    {"word":"Pinterest","clues":["Ideas","Tablero","Fotos","Inspiración","Pin"],"category":"social_media_and_streamers"},
    {"word":"OnlyFans","clues":["Suscripción","Contenido","Pago","Adultos","Privado"],"category":"social_media_and_streamers"},
    {"word":"Thread","clues":["Hilo","Twitter","Historia","Mensajes","Texto"],"category":"social_media_and_streamers"},
    {"word":"Ban","clues":["Expulsión","Prohibido","Cuenta","Reglas","Bloqueo"],"category":"social_media_and_streamers"},
    {"word":"Mod","clues":["Moderador","Chat","Ayuda","Reglas","Stream"],"category":"social_media_and_streamers"},
    {"word":"Donación","clues":["Dinero","Streamer","Apoyo","Bits","Alerta"],"category":"social_media_and_streamers"},
    {"word":"Setup","clues":["Escritorio","PC","Luces","Silla","Cámara"],"category":"social_media_and_streamers"},
    {"word":"Vlog","clues":["Vídeo","Vida","Cámara","Diario","YouTube"],"category":"social_media_and_streamers"},
    {"word":"Trend","clues":["Tendencia","Moda","Viral","Popular","Redes"],"category":"social_media_and_streamers"},
    {"word":"Challenge","clues":["Reto","Viral","TikTok","Participar","Vídeo"],"category":"social_media_and_streamers"},
    {"word":"Emoji","clues":["Cara","Dibujo","Mensaje","Símbolo","Color"],"category":"social_media_and_streamers"},
    {"word":"Feed","clues":["Perfil","Muro","Fotos","Inicio","Scroll"],"category":"social_media_and_streamers"},
    {"word":"Sticker","clues":["Pegatina","WhatsApp","Imagen","Chat","Gracia"],"category":"social_media_and_streamers"},
    {"word":"Luisito Comunica","clues":["Viajes","YouTube","México","Maleta","Cámara"],"category":"social_media_and_streamers"},
    {"word":"PewDiePie","clues":["YouTube","Gaming","Suecia","Rey","Suscriptores"],"category":"social_media_and_streamers"},
    {"word":"Khaby Lame","clues":["TikTok","Manos","Mudo","Sencillo","Viral"],"category":"social_media_and_streamers"},
    {"word":"BeReal","clues":["Foto","Real","Notificación","Cámara","Momento"],"category":"social_media_and_streamers"},
    {"word":"Reel","clues":["Instagram","Vídeo","Corto","Música","Vertical"],"category":"social_media_and_streamers"},
    {"word":"Live","clues":["Directo","Vivo","Cámara","Interactuar","Tiempo real"],"category":"social_media_and_streamers"},
    {"word":"Algorithm","clues":["Algoritmo","Contenido","Feed","Orden","Matemáticas"],"category":"social_media_and_streamers"},
    {"word":"DM","clues":["Mensaje","Privado","Chat","Directo","Redes"],"category":"social_media_and_streamers"},
    {"word":"Ghosting","clues":["Ignorar","Mensaje","Desaparecer","Silencio","Visto"],"category":"social_media_and_streamers"},
    {"word":"Bio","clues":["Perfil","Descripción","Texto","Información","Enlace"],"category":"social_media_and_streamers"},
    {"word":"Viral","clues":["Popular","Rápido","Compartir","Internet","Tendencia"],"category":"social_media_and_streamers"},
    {"word":"Filter","clues":["Foto","Efecto","Instagram","Color","Cámara"],"category":"social_media_and_streamers"},
    {"word":"Story","clues":["Historia","Instagram","Efímero","Fotos","Vídeos"],"category":"social_media_and_streamers"},
    {"word":"Subtítulo","clues":["Texto","Vídeo","Traducción","YouTube","Accesibilidad"],"category":"social_media_and_streamers"},
    {"word":"Vlogger","clues":["Vlog","YouTube","Vida","Cámara","Diario"],"category":"social_media_and_streamers"},
    {"word":"Collab","clues":["Colaboración","Unión","Contenido","Juntos","Redes"],"category":"social_media_and_streamers"},
    {"word":"Shoutout","clues":["Mención","Agradecimiento","Redes","Apoyo","Visibilidad"],"category":"social_media_and_streamers"}
  ]
}